httpx_curl_cffi-0.1.4.dist-info/METADATA
httpx_curl_cffi-0.1.4.dist-info/WHEEL
httpx_curl_cffi-0.1.4.dist-info/entry_points.txt
httpx_curl_cffi-0.1.4.dist-info/licenses/LICENSE
httpx_curl_cffi/__init__.py
httpx_curl_cffi/py.typed
httpx_curl_cffi/transport.py
httpx_curl_cffi-0.1.4.dist-info/RECORD
