Metadata-Version: 2.4
Name: httpx-curl-cffi
Version: 0.1.4
Summary: httpx transport for curl_cffi (python bindings for curl-impersonate)
Author-Email: Victor Gavro <vgavro@gmail.com>
License-Expression: BSD-3-Clause
License-File: LICENSE
Classifier: Development Status :: 4 - Beta
Classifier: Environment :: Web Environment
Classifier: Framework :: AsyncIO
Classifier: Intended Audience :: Developers
Classifier: Operating System :: OS Independent
Classifier: Typing :: Typed
Classifier: Programming Language :: Python :: 3
Classifier: Programming Language :: Python :: 3 :: Only
Classifier: Programming Language :: Python :: 3.10
Classifier: Programming Language :: Python :: 3.11
Classifier: Programming Language :: Python :: 3.12
Classifier: Programming Language :: Python :: 3.13
Classifier: Topic :: Internet :: WWW/HTTP
Project-URL: Homepage, https://github.com/vgavro/httpx-curl-cffi
Project-URL: Repository, https://github.com/vgavro/httpx-curl-cffi
Requires-Python: >=3.10
Requires-Dist: curl-cffi>=0.7.0
Requires-Dist: httpx>=0.21.0
Requires-Dist: typing-extensions>=4.12.2
